demo/__init__.py
demo/demo1-verify-basics.py
demo/demo2-verify-output-to-file.py
demo/demo3-verify-filename.py
demo/demo4-verify-to-gitignore.py
demo/demo5-add-new-detected-words.py
dev_utils/__init__.py
dev_utils/dev_sec.py
dev_utils/sec_names.py
src/__init__.py
src/dev_sec.py
src/sec_names.py
tests/__init__.py
tests/test_main_functions.py
tests/test_sec_names.py
ndevsecuritychecker-0.1.1.dist-info/METADATA
ndevsecuritychecker-0.1.1.dist-info/WHEEL
ndevsecuritychecker-0.1.1.dist-info/top_level.txt
ndevsecuritychecker-0.1.1.dist-info/RECORD
