Metadata-Version: 2.2
Name: ndevsecuritychecker
Version: 0.1.1
Summary: A project module for my coding class, that will serve me after.
Home-page: https://gitlab.com/bts-ciel-a1/base-project-structure/-/tree/ige/dev_utils?ref_type=heads
Download-URL: https://pypi.org/
Author: Ilian
Keywords: dev,utils,Checker,Security
Requires-Dist: colorama<=0.4.6
Requires-Dist: pytest<=8.3.4
Requires-Dist: pytest-cov<=6.0.0
Requires-Dist: rich<=13.9.4
Dynamic: author
Dynamic: description
Dynamic: description-content-type
Dynamic: download-url
Dynamic: home-page
Dynamic: keywords
Dynamic: requires-dist
Dynamic: summary
